pydantic_resolve/__init__.py
pydantic_resolve/constant.py
pydantic_resolve/core.py
pydantic_resolve/exceptions.py
pydantic_resolve/resolver.py
pydantic_resolve/util.py
pydantic2_resolve-2.1.1.dist-info/LICENSE
pydantic2_resolve-2.1.1.dist-info/METADATA
pydantic2_resolve-2.1.1.dist-info/WHEEL
pydantic2_resolve-2.1.1.dist-info/RECORD
