Metadata-Version: 2.1
Name: pydantic2-resolve
Version: 2.1.1
Summary: create nested data structure easily
Home-page: https://github.com/allmonday/pydantic2_resolve
License: MIT
Keywords: pydantic2,fastapi
Author: tangkikodo
Author-email: allmonday@126.com
Requires-Python: >=3.7,<4.0
Classifier: License :: OSI Approved :: MIT License
Classifier: Programming Language :: Python :: 3
Classifier: Programming Language :: Python :: 3.7
Classifier: Programming Language :: Python :: 3.8
Classifier: Programming Language :: Python :: 3.9
Classifier: Programming Language :: Python :: 3.10
Classifier: Programming Language :: Python :: 3.11
Requires-Dist: aiodataloader (>=0.4.0,<0.5.0)
Requires-Dist: pydantic (>=2.4,<3.0)
Project-URL: Repository, https://github.com/allmonday/pydantic2_resolve
